libssettings/__init__.py
libssettings/connection.py
libssettings/connection_handler.py
libssettings/exceptions.py
libssettings/hooks.py
libssettings/logger.py
libssettings/rules.py
libssettings/server.py
libssettings/settings.py
libssettings/utils.py
libssettings/version.py
libssettings/scripts/__init__.py
libssettings/scripts/main.py
simplesettingsdaemon-0.0.2.data/data/share/man/man1/ssettings.1
simplesettingsdaemon-0.0.2.data/scripts/ssettings
simplesettingsdaemon-0.0.2.data/scripts/ssettingsd
simplesettingsdaemon-0.0.2.dist-info/LICENSE
simplesettingsdaemon-0.0.2.dist-info/METADATA
simplesettingsdaemon-0.0.2.dist-info/WHEEL
simplesettingsdaemon-0.0.2.dist-info/top_level.txt
simplesettingsdaemon-0.0.2.dist-info/RECORD
