Metadata-Version: 2.1
Name: simplesettingsdaemon
Version: 0.0.2
Summary: Simple settings daemon for linux
Home-page: https://github.com/QazmoQwerty/simple-settings-daemon
Author: Shalev Don Meiri
Author-email: sdonmeiri@gmail.com
License: MIT
Project-URL: Bug Tracker, https://github.com/QazmoQwerty/simple-settings-daemon/issues
Platform: UNKNOWN
Classifier: Programming Language :: Python :: 3
Classifier: License :: OSI Approved :: MIT License
Classifier: Operating System :: POSIX :: Linux
Requires-Python: >=3.7
License-File: LICENSE
